pychisel/__init__.py
pychisel/core.py
pychisel/exceptions.py
pychisel/utils.py
pychisel-0.3.1.dist-info/METADATA
pychisel-0.3.1.dist-info/WHEEL
pychisel-0.3.1.dist-info/top_level.txt
pychisel-0.3.1.dist-info/RECORD
